<?xml version="1.0" encoding="UTF-8"?>

<xwikidoc>
  <web>XWiki</web>
  <name>UserNotificationConfigurationClass</name>
  <language/>
  <defaultLanguage/>
  <translation>0</translation>
  <parent>Main.UserNotificationAdmin</parent>
  <creator>xwiki:XWiki.Admin</creator>
  <author>xwiki:XWiki.Admin</author>
  <customClass/>
  <contentAuthor>xwiki:XWiki.Admin</contentAuthor>
  <creationDate>1380980753000</creationDate>
  <date>1380981043000</date>
  <contentUpdateDate>1380981043000</contentUpdateDate>
  <version>1.1</version>
  <title/>
  <defaultTemplate/>
  <validationScript/>
  <comment/>
  <minorEdit>false</minorEdit>
  <syntaxId>xwiki/2.1</syntaxId>
  <hidden>false</hidden>
  <class>
    <name>XWiki.UserNotificationConfigurationClass</name>
    <customClass/>
    <customMapping/>
    <defaultViewSheet/>
    <defaultEditSheet/>
    <defaultWeb/>
    <nameField/>
    <validationScript/>
    <usercreation.enabled>
      <customDisplay/>
      <defaultValue/>
      <disabled>0</disabled>
      <displayFormType>select</displayFormType>
      <displayType/>
      <name>usercreation.enabled</name>
      <number>1</number>
      <prettyName>User creation notification enabled</prettyName>
      <unmodifiable>0</unmodifiable>
      <validationMessage/>
      <validationRegExp/>
      <classType>com.xpn.xwiki.objects.classes.BooleanClass</classType>
    </usercreation.enabled>
    <usercreation.template>
      <cache>0</cache>
      <classname>XWiki.Mail</classname>
      <customDisplay/>
      <disabled>0</disabled>
      <displayType>select</displayType>
      <idField/>
      <multiSelect>0</multiSelect>
      <name>usercreation.template</name>
      <number>2</number>
      <picker>0</picker>
      <prettyName>User creation notification template</prettyName>
      <relationalStorage>0</relationalStorage>
      <separator> </separator>
      <separators/>
      <size>1</size>
      <sort>none</sort>
      <sql/>
      <unmodifiable>0</unmodifiable>
      <validationMessage/>
      <validationRegExp/>
      <valueField/>
      <classType>com.xpn.xwiki.objects.classes.PageClass</classType>
    </usercreation.template>
  </class>
  <content/>
</xwikidoc>
